Ed.py
thonnycontrib/backend/edison_backend/__init__.py
thonnycontrib/backend/edison_backend/EdPy/EdAsm.py
thonnycontrib/backend/edison_backend/EdPy/EdPy.py
thonnycontrib/backend/edison_backend/EdPy/LICENSE
thonnycontrib/backend/edison_backend/EdPy/TranStrings.py
thonnycontrib/backend/edison_backend/EdPy/en_lang.json
thonnycontrib/backend/edison_backend/EdPy/lib/__init__.py
thonnycontrib/backend/edison_backend/EdPy/lib/audio.py
thonnycontrib/backend/edison_backend/EdPy/lib/compiler.py
thonnycontrib/backend/edison_backend/EdPy/lib/edpy_code.py
thonnycontrib/backend/edison_backend/EdPy/lib/edpy_values.py
thonnycontrib/backend/edison_backend/EdPy/lib/hl_parser.py
thonnycontrib/backend/edison_backend/EdPy/lib/io.py
thonnycontrib/backend/edison_backend/EdPy/lib/optimiser.py
thonnycontrib/backend/edison_backend/EdPy/lib/parser.py
thonnycontrib/backend/edison_backend/EdPy/lib/program.py
thonnycontrib/backend/edison_backend/EdPy/lib/token_assembler.py
thonnycontrib/backend/edison_backend/EdPy/lib/token_bits.py
thonnycontrib/backend/edison_backend/EdPy/lib/tokens.py
thonnycontrib/backend/edison_backend/EdPy/lib/util.py
thonnycontrib/edison/__init__.py
thonnycontrib/edison/res/tools.program_edison.png
thonnycontrib/edison/res/tools.program_edison_2x.png
thonny_edison-1.1.0.dist-info/LICENSE.txt
thonny_edison-1.1.0.dist-info/METADATA
thonny_edison-1.1.0.dist-info/WHEEL
thonny_edison-1.1.0.dist-info/top_level.txt
thonny_edison-1.1.0.dist-info/RECORD
