Metadata-Version: 2.1
Name: thonny-edison
Version: 1.1.0
Summary: A plug-in which adds Edison robot support for Thonny
Home-page: https://github.com/thonny/thonny-edison/
Author: Aivar Annamaa
License: GPL
Keywords: IDE education programming robotics Edison
Platform: Windows
Platform: macOS
Platform: Linux
Classifier: Environment :: MacOS X
Classifier: Environment :: Win32 (MS Windows)
Classifier: Environment :: X11 Applications
Classifier: Intended Audience :: Developers
Classifier: Intended Audience :: Education
Classifier: Intended Audience :: End Users/Desktop
Classifier: License :: Freeware
Classifier: License :: OSI Approved :: GNU General Public License (GPL)
Classifier: Natural Language :: English
Classifier: Operating System :: MacOS
Classifier: Operating System :: Microsoft :: Windows
Classifier: Operating System :: POSIX
Classifier: Operating System :: POSIX :: Linux
Classifier: Programming Language :: Python
Classifier: Programming Language :: Python :: 3
Classifier: Programming Language :: Python :: 3 :: Only
Classifier: Programming Language :: Python :: 3.7
Classifier: Programming Language :: Python :: 3.8
Classifier: Programming Language :: Python :: 3.9
Classifier: Programming Language :: Python :: 3.10
Classifier: Topic :: Education
Classifier: Topic :: Software Development
Requires-Python: >=3.7
License-File: LICENSE.txt
Requires-Dist: thonny (>=3.2.1)
